hyperon_das/__init__.py
hyperon_das/cache.py
hyperon_das/client.py
hyperon_das/constants.py
hyperon_das/das.py
hyperon_das/decorators.py
hyperon_das/exceptions.py
hyperon_das/logger.py
hyperon_das/pattern_matcher/__init__.py
hyperon_das/pattern_matcher/constants.py
hyperon_das/pattern_matcher/pattern_matcher.py
hyperon_das/query_engines.py
hyperon_das/utils.py
a4be0643f1d98573b97cdca98a65347dd-0.1.0.dist-info/METADATA
a4be0643f1d98573b97cdca98a65347dd-0.1.0.dist-info/WHEEL
a4be0643f1d98573b97cdca98a65347dd-0.1.0.dist-info/RECORD
