Metadata-Version: 2.1
Name: a4be0643f1d98573b97cdca98a65347dd
Version: 0.1.0
Summary: Query Engine API for Distributed AtomSpace
Author: marcocapozzoli
Author-email: marcocapozzoli90@gmail.com
Requires-Python: >=3.8.5,<4.0.0
Classifier: Programming Language :: Python :: 3
Classifier: Programming Language :: Python :: 3.9
Classifier: Programming Language :: Python :: 3.10
Classifier: Programming Language :: Python :: 3.11
Requires-Dist: hyperon_das_atomdb (>=0.2.4,<0.3.0)
Requires-Dist: python-dotenv (>=1.0.0,<2.0.0)
Requires-Dist: requests (>=2.31.0,<3.0.0)
